tpower5score/__init__.py
tpower5score/evaluator.py
tpower5score/judges.py
tpower5score/scoring.py
tpower5score-0.1.1.dist-info/licenses/LICENSE
tpower5score-0.1.1.dist-info/METADATA
tpower5score-0.1.1.dist-info/WHEEL
tpower5score-0.1.1.dist-info/top_level.txt
tpower5score-0.1.1.dist-info/RECORD
