Metadata-Version: 2.4
Name: tpower5score
Version: 0.1.1
Summary: An automatic evaluation package for assessing the quality of LLM-generated multi-document topic sets.
Author-email: Itamar Trainin <itamar.trainin@mail.huji.ac.il>, Omri Abend <omri.abend@mail.huji.ac.il>
License: MIT License
Project-URL: Homepage, https://github.com/itamartrainin/Tpower5Score
Requires-Python: >=3.11
License-File: LICENSE
Requires-Dist: numpy~=1.26.4
Requires-Dist: tqdm~=4.67.0
Requires-Dist: litellm~=1.73.0
Requires-Dist: scipy~=1.13.1
Dynamic: license-file
